happyx/__init__.py
happyx/constants.py
happyx/happyx_unix_amd64.so
happyx/happyx_unix_arm64.so
happyx/happyx_win.pyd
happyx/server.py
happyx-4.7.4.dist-info/METADATA
happyx-4.7.4.dist-info/WHEEL
happyx-4.7.4.dist-info/top_level.txt
happyx-4.7.4.dist-info/RECORD
