Metadata-Version: 2.2
Name: happyx
Version: 4.7.4
Summary: HappyX web framework bindings for Python 🐍
Home-page: https://github.com/HapticX/happyx/tree/master/bindings/python
Author: Ethosa
Author-email: social.ethosa@gmail.com
Maintainer: HapticX
Maintainer-email: hapticx.company@gmail.com
License: MIT
Classifier: Development Status :: 5 - Production/Stable
Classifier: Topic :: Software Development :: Libraries :: Application Frameworks
Classifier: License :: OSI Approved :: MIT License
Classifier: Operating System :: OS Independent
Classifier: Programming Language :: Python :: 3.7
Classifier: Programming Language :: Python :: 3.8
Classifier: Programming Language :: Python :: 3.9
Classifier: Programming Language :: Python :: 3.10
Classifier: Programming Language :: Python :: 3.11
Classifier: Programming Language :: Python :: 3.12
Requires-Dist: jinja2
Dynamic: author
Dynamic: author-email
Dynamic: classifier
Dynamic: description
Dynamic: description-content-type
Dynamic: home-page
Dynamic: license
Dynamic: maintainer
Dynamic: maintainer-email
Dynamic: requires-dist
Dynamic: summary
